seqo/__init__.py
seqo-0.1.2.dist-info/licenses/LICENSE
seqo-0.1.2.dist-info/METADATA
seqo-0.1.2.dist-info/WHEEL
seqo-0.1.2.dist-info/top_level.txt
seqo-0.1.2.dist-info/RECORD
